recordio/__init__.py
recordio/librecordio.cpython-36m-x86_64-linux-gnu.h
recordio/librecordio.cpython-36m-x86_64-linux-gnu.so
recordio/recordio.py
pyrecordio-0.0.7.dist-info/METADATA
pyrecordio-0.0.7.dist-info/WHEEL
pyrecordio-0.0.7.dist-info/top_level.txt
pyrecordio-0.0.7.dist-info/RECORD
