Metadata-Version: 2.1
Name: pyrecordio
Version: 0.0.7
Summary: recordio file format support
Home-page: https://github.com/wangkuiyi/recordio
Author: UNKNOWN
Author-email: UNKNOWN
License: Apache 2.0
Platform: UNKNOWN
